.flake8
.gitignore
.travis.yml
CHANGELOG.rst
LICENSE
README.rst
pip-10-install.py
pyproject.toml
setup.cfg
setup.py
tox.ini
mongo_connector/__init__.py
mongo_connector/command_helper.py
mongo_connector/compat.py
mongo_connector/config.py
mongo_connector/connector.py
mongo_connector/constants.py
mongo_connector/errors.py
mongo_connector/get_last_oplog_timestamp.py
mongo_connector/gridfs_file.py
mongo_connector/locking_dict.py
mongo_connector/namespace_config.py
mongo_connector/oplog_manager.py
mongo_connector/test_utils.py
mongo_connector/util.py
mongo_connector/version.py
mongo_connector/doc_managers/__init__.py
mongo_connector/doc_managers/doc_manager_base.py
mongo_connector/doc_managers/doc_manager_simulator.py
mongo_connector/doc_managers/formatters.py
mongo_connector/doc_managers/mongo_doc_manager.py
mongo_connector/service/System V init
mongo_connector/service/__init__.py
mongo_connector/service/config.json
mongo_connector/service/system-v.py
mongo_connector_transaction.egg-info/PKG-INFO
mongo_connector_transaction.egg-info/SOURCES.txt
mongo_connector_transaction.egg-info/dependency_links.txt
mongo_connector_transaction.egg-info/entry_points.txt
mongo_connector_transaction.egg-info/requires.txt
mongo_connector_transaction.egg-info/top_level.txt
tests/__init__.py
tests/test_command_replication.py
tests/test_config.py
tests/test_connector_sharded.py
tests/test_doc_manager_base.py
tests/test_filter_fields.py
tests/test_formatters.py
tests/test_gridfs_file.py
tests/test_mongo.py
tests/test_mongo_connector.py
tests/test_mongo_doc_manager.py
tests/test_namespace_config.py
tests/test_oplog_manager.py
tests/test_oplog_manager_sharded.py
tests/test_oplog_manager_wildcard.py
tests/test_rollbacks.py
tests/test_synchronizer.py
tests/test_util.py
tests/lib/dummy.pwd