Metadata-Version: 2.1
Name: mongo-connector-transaction
Version: 1.4.0
Summary: Mongo Connector Transaction Support
Home-page: https://github.com/AmrAdelKhalil/mongo-connector
Author: MongoDB, Inc.
Author-email: amradelkhalil@gmail.com
License: UNKNOWN
Keywords: mongo-connector,mongo,mongodb,solr,elasticsearch
Platform: any
Classifier: Development Status :: 4 - Beta
Classifier: Intended Audience :: Developers
Classifier: License :: OSI Approved :: Apache Software License
Classifier: Programming Language :: Python :: 3
Classifier: Topic :: Database
Classifier: Topic :: Software Development :: Libraries :: Python Modules
Classifier: Operating System :: Unix
Classifier: Operating System :: MacOS :: MacOS X
Classifier: Operating System :: Microsoft :: Windows
Classifier: Operating System :: POSIX
Classifier: 
Requires-Python: >=3.4
Provides-Extra: solr
Provides-Extra: elastic
Provides-Extra: elastic-aws
Provides-Extra: elastic2
Provides-Extra: elastic5
Provides-Extra: elastic2-aws
License-File: LICENSE
